./LICENSE
./PKG-INFO
./README.md
./currency_mcp_server.py
currency_mcp-0.3.0.dist-info/METADATA
currency_mcp-0.3.0.dist-info/WHEEL
currency_mcp-0.3.0.dist-info/entry_points.txt
currency_mcp-0.3.0.dist-info/licenses/LICENSE
currency_mcp-0.3.0.dist-info/RECORD
