Metadata-Version: 2.4
Name: currency-mcp
Version: 0.3.0
Summary: A Model Context Protocol (MCP) server for currency conversion using the Frankfurter API
Project-URL: Homepage, https://github.com/vanloc1808/currency-mcp
Project-URL: Repository, https://github.com/vanloc1808/currency-mcp
Project-URL: Issues, https://github.com/vanloc1808/currency-mcp/issues
Project-URL: Documentation, https://github.com/vanloc1808/currency-mcp#readme
Author-email: Van-Loc Nguyen <vanloc1808@gmail.com>
License: MIT
License-File: LICENSE
Keywords: ai-tools,currency,exchange-rate,mcp,model-context-protocol
Classifier: Development Status :: 4 - Beta
Classifier: Intended Audience :: Developers
Classifier: License :: OSI Approved :: MIT License
Classifier: Programming Language :: Python :: 3
Classifier: Programming Language :: Python :: 3.11
Classifier: Programming Language :: Python :: 3.12
Classifier: Programming Language :: Python :: 3.13
Classifier: Topic :: Office/Business :: Financial
Classifier: Topic :: Software Development :: Libraries :: Python Modules
Requires-Python: >=3.11
Requires-Dist: fastmcp
Requires-Dist: httpx
Requires-Dist: mcp[cli]
Requires-Dist: pydantic
